pymodaq_plugins_BNC575/__init__.py
pymodaq_plugins_BNC575/utils.py
pymodaq_plugins_BNC575/daq_move_plugins/__init__.py
pymodaq_plugins_BNC575/daq_move_plugins/daq_move_Template.py
pymodaq_plugins_BNC575/daq_viewer_plugins/__init__.py
pymodaq_plugins_BNC575/daq_viewer_plugins/plugins_0D/__init__.py
pymodaq_plugins_BNC575/daq_viewer_plugins/plugins_0D/daq_0Dviewer_BNC575.py
pymodaq_plugins_BNC575/daq_viewer_plugins/plugins_1D/__init__.py
pymodaq_plugins_BNC575/daq_viewer_plugins/plugins_1D/daq_1Dviewer_Template.py
pymodaq_plugins_BNC575/daq_viewer_plugins/plugins_2D/__init__.py
pymodaq_plugins_BNC575/daq_viewer_plugins/plugins_2D/daq_2Dviewer_Template.py
pymodaq_plugins_BNC575/daq_viewer_plugins/plugins_ND/__init__.py
pymodaq_plugins_BNC575/exporters/__init__.py
pymodaq_plugins_BNC575/extensions/__init__.py
pymodaq_plugins_BNC575/extensions/myextension.py
pymodaq_plugins_BNC575/hardware/__init__.py
pymodaq_plugins_BNC575/hardware/bnc_commands.py
pymodaq_plugins_BNC575/hardware/device.py
pymodaq_plugins_BNC575/models/PIDModelTemplate.py
pymodaq_plugins_BNC575/models/__init__.py
pymodaq_plugins_BNC575/resources/VERSION
pymodaq_plugins_BNC575/resources/__init__.py
pymodaq_plugins_BNC575/resources/config_template.toml
pymodaq_plugins_BNC575/scanners/__init__.py
pymodaq_plugins_BNC575-0.0.1.dist-info/LICENSE
pymodaq_plugins_BNC575-0.0.1.dist-info/METADATA
pymodaq_plugins_BNC575-0.0.1.dist-info/WHEEL
pymodaq_plugins_BNC575-0.0.1.dist-info/entry_points.txt
pymodaq_plugins_BNC575-0.0.1.dist-info/top_level.txt
pymodaq_plugins_BNC575-0.0.1.dist-info/RECORD
